pyscemu-0.9.3.dist-info/METADATA
pyscemu-0.9.3.dist-info/WHEEL
pyscemu/__init__.py
pyscemu/pyscemu.cpython-39-darwin.so
pyscemu-0.9.3.dist-info/RECORD
