Metadata-Version: 2.3
Name: pyscemu
Version: 0.9.3
Classifier: Programming Language :: Rust
Classifier: Programming Language :: Python :: Implementation :: CPython
Classifier: Programming Language :: Python :: Implementation :: PyPy
Summary: x86 32/64bits and system internals emulator, for securely emulating malware and other stuff.
Requires-Python: >=3.7
